opensoundscape/__init__.py
opensoundscape/annotations.py
opensoundscape/audio.py
opensoundscape/data_selection.py
opensoundscape/localization/__init__.py
opensoundscape/localization/audiomoth_sync.py
opensoundscape/localization/localization_algorithms.py
opensoundscape/localization/position_estimate.py
opensoundscape/localization/spatial_event.py
opensoundscape/localization/synchronized_recorder_array.py
opensoundscape/localization/utils.py
opensoundscape/logging.py
opensoundscape/metrics.py
opensoundscape/ml/__init__.py
opensoundscape/ml/cam.py
opensoundscape/ml/cnn.py
opensoundscape/ml/cnn_architectures.py
opensoundscape/ml/dataloaders.py
opensoundscape/ml/datasets.py
opensoundscape/ml/lightning.py
opensoundscape/ml/loss.py
opensoundscape/ml/safe_dataset.py
opensoundscape/ml/sampling.py
opensoundscape/ml/shallow_classifier.py
opensoundscape/ml/utils.py
opensoundscape/preprocess/__init__.py
opensoundscape/preprocess/action_functions.py
opensoundscape/preprocess/actions.py
opensoundscape/preprocess/img_augment.py
opensoundscape/preprocess/io.py
opensoundscape/preprocess/overlay.py
opensoundscape/preprocess/preprocessors.py
opensoundscape/preprocess/tensor_augment.py
opensoundscape/preprocess/utils.py
opensoundscape/ribbit.py
opensoundscape/sample.py
opensoundscape/sample_data/birds_10s.wav
opensoundscape/sample_data.py
opensoundscape/signal_processing.py
opensoundscape/spectrogram.py
opensoundscape/utils.py
opensoundscape-0.12.1.dist-info/LICENSE
opensoundscape-0.12.1.dist-info/METADATA
opensoundscape-0.12.1.dist-info/WHEEL
opensoundscape-0.12.1.dist-info/entry_points.txt
opensoundscape-0.12.1.dist-info/RECORD
