Metadata-Version: 2.3
Name: opensoundscape
Version: 0.12.1
Summary: Open source, scalable acoustic data analysis for ecology and conservation
License: MIT
Author: Sam Lapp
Author-email: sammlapp@gmail.com
Requires-Python: >=3.10, !=2.7.*, !=3.0.*, !=3.1.*, !=3.2.*, !=3.3.*, !=3.4.*, !=3.5.*, !=3.6.*, !=3.7.*, !=3.8.*, !=3.9.*
Classifier: License :: OSI Approved :: MIT License
Classifier: Programming Language :: Python :: 3
Classifier: Programming Language :: Python :: 3.10
Classifier: Programming Language :: Python :: 3.12
Classifier: Programming Language :: Python :: 3.13
Provides-Extra: tensorflow
Requires-Dist: Deprecated (>=1.2.13,<2.0.0)
Requires-Dist: Jinja2 (>=3.1.6)
Requires-Dist: aiohttp (>=3.12.14)
Requires-Dist: aru-metadata-parser (>=0.1.0)
Requires-Dist: certifi (>=2024.7.4)
Requires-Dist: docopt (>=0.6.2)
Requires-Dist: gitpython (>=3.1.41)
Requires-Dist: grad-cam (>=1.5.0)
Requires-Dist: h11 (>=0.16.0)
Requires-Dist: ipykernel (>=5.2.0)
Requires-Dist: ipython (>=7.34.0)
Requires-Dist: ipywidgets (>=8.1.0)
Requires-Dist: joblib (>=1.2.0)
Requires-Dist: jupyter-server (>=2.11.2)
Requires-Dist: jupyterlab (>=2.1.4)
Requires-Dist: librosa (>=0.11.0)
Requires-Dist: lightning (>=2.2.5)
Requires-Dist: llvmlite (>=0.44.0)
Requires-Dist: matplotlib (>=3.9.4)
Requires-Dist: matplotlib-inline (>=0.1.7)
Requires-Dist: noisereduce (>=3.0.2)
Requires-Dist: numba (>=0.57.0)
Requires-Dist: numpy (>2.0)
Requires-Dist: pandas (>=1.3)
Requires-Dist: pillow (>=9.4.0)
Requires-Dist: protobuf (>=5.29.5)
Requires-Dist: pywavelets (>=1.2.0)
Requires-Dist: requests (>=2.32.4)
Requires-Dist: schema (>=0.7.2)
Requires-Dist: scikit-image (>=0.17.2)
Requires-Dist: scikit-learn (>=0.24.2)
Requires-Dist: scipy (>=1.15)
Requires-Dist: sentry-sdk (>=2.8.0)
Requires-Dist: setuptools (>=78.1.1)
Requires-Dist: soundfile (>=0.13.1)
Requires-Dist: torch (>=2.5.1)
Requires-Dist: torchvision (>=0.15.1)
Requires-Dist: tornado (>=6.5.1)
Requires-Dist: tqdm (>=4.66.1)
Requires-Dist: urllib3 (>=2.5.0)
Requires-Dist: wandb (>=0.17.0)
Requires-Dist: werkzeug (>=3.0.1)
Project-URL: Repository, https://github.com/jkitzes/opensoundscape
